whiskerrag_client/__init__.py
whiskerrag_client/agent.py
whiskerrag_client/chunk_client.py
whiskerrag_client/http_client.py
whiskerrag_client/knowledge_client.py
whiskerrag_client/retrieval_client.py
whiskerrag_client/space_client.py
whiskerrag_client/task_client.py
whiskerrag_types/__init__.py
whiskerrag_types/interface/__init__.py
whiskerrag_types/interface/async_utils.py
whiskerrag_types/interface/db_engine_plugin_interface.py
whiskerrag_types/interface/embed_interface.py
whiskerrag_types/interface/fastapi_plugin_interface.py
whiskerrag_types/interface/llm_interface.py
whiskerrag_types/interface/loader_interface.py
whiskerrag_types/interface/parser_interface.py
whiskerrag_types/interface/retriever_interface.py
whiskerrag_types/interface/settings_interface.py
whiskerrag_types/interface/task_engine_plugin_interface.py
whiskerrag_types/model/__init__.py
whiskerrag_types/model/agent.py
whiskerrag_types/model/api_key.py
whiskerrag_types/model/artifact_index.py
whiskerrag_types/model/chunk.py
whiskerrag_types/model/converter.py
whiskerrag_types/model/knowledge.py
whiskerrag_types/model/knowledge_create.py
whiskerrag_types/model/knowledge_source.py
whiskerrag_types/model/language.py
whiskerrag_types/model/multi_modal.py
whiskerrag_types/model/page.py
whiskerrag_types/model/permission.py
whiskerrag_types/model/retrieval.py
whiskerrag_types/model/rule.py
whiskerrag_types/model/space.py
whiskerrag_types/model/splitter.py
whiskerrag_types/model/tag.py
whiskerrag_types/model/tagging.py
whiskerrag_types/model/task.py
whiskerrag_types/model/tenant.py
whiskerrag_types/model/timeStampedModel.py
whiskerrag_types/model/utils.py
whiskerrag_types/model/wiki.py
whiskerrag_types/py.typed
whiskerrag_utils/__init__.py
whiskerrag_utils/embedding/__init__.py
whiskerrag_utils/embedding/openai.py
whiskerrag_utils/helper/yuque.py
whiskerrag_utils/llm/example_llm.py
whiskerrag_utils/loader/__init__.py
whiskerrag_utils/loader/artifacts_extract.py
whiskerrag-0.3.7.dist-info/LICENSE
whiskerrag-0.3.7.dist-info/METADATA
whiskerrag-0.3.7.dist-info/WHEEL
whiskerrag-0.3.7.dist-info/entry_points.txt
whiskerrag-0.3.7.dist-info/RECORD
