Metadata-Version: 2.3
Name: whiskerrag
Version: 0.3.7
Summary: A utlity package for RAG operations
Author: petercat.ai
Author-email: antd.antgroup@gmail.com
Requires-Python: >=3.9,<4.0
Classifier: Development Status :: 3 - Alpha
Classifier: Intended Audience :: Developers
Classifier: License :: OSI Approved :: MIT License
Classifier: Programming Language :: Python :: 3
Classifier: Programming Language :: Python :: 3.9
Classifier: Programming Language :: Python :: 3.10
Classifier: Programming Language :: Python :: 3.11
Classifier: Programming Language :: Python :: 3.12
Classifier: Programming Language :: Python :: 3.13
Requires-Dist: boto3 (>=1.38.13,<2.0.0)
Requires-Dist: chardet (>=5.2.0,<6.0.0)
Requires-Dist: deprecated (>=1.2.18,<2.0.0)
Requires-Dist: gitpython (>=3.1.44,<4.0.0)
Requires-Dist: langchain (>=0.2.12)
Requires-Dist: langchain-community (>=0.2.11)
Requires-Dist: langchain-core (>=0.2.28)
Requires-Dist: langchain-openai (>=0.1.20)
Requires-Dist: openai (>=1.91.0,<2.0.0)
Requires-Dist: pydantic (>=2.0.0,<3.0.0)
Requires-Dist: python-dateutil (>=2.8.2)
Requires-Dist: requests (>=2.32.3)
Requires-Dist: typing-extensions (>=4.12.2)
Requires-Dist: urllib3 (>=1.25.3,<3.0.0)
